README.md
setup.py
alipan/__init__.py
alipan/__main__.py
alipan/aligo_utils.py
alipan/help.py
alipan.egg-info/PKG-INFO
alipan.egg-info/SOURCES.txt
alipan.egg-info/dependency_links.txt
alipan.egg-info/entry_points.txt
alipan.egg-info/requires.txt
alipan.egg-info/top_level.txt