Metadata-Version: 1.0
Name: alipan
Version: 1.3.8
Summary: Commandline tools for aliyundrive
Home-page: https://github.com/qicongsheng/alipan
Author: qicongsheng
Author-email: qicongsheng@outlook.com
License: MIT License
Keywords: alipan
Platform: any
